fast_eda/__init__.py
fast_eda/fast_eda.py
very_fast_eda-3.0.0.dist-info/LICENSE
very_fast_eda-3.0.0.dist-info/METADATA
very_fast_eda-3.0.0.dist-info/WHEEL
very_fast_eda-3.0.0.dist-info/RECORD
