Metadata-Version: 2.3
Name: very_fast_eda
Version: 3.0.0
Summary: A packckage for performing fast EDA operations on any pandas data frames.
License: MIT
Author: Tien Nguyen, Eugene You, Gilbert Akuja, Shawn Xiao Hu
Requires-Python: >=3.11,<4.0
Classifier: License :: OSI Approved :: MIT License
Classifier: Programming Language :: Python :: 3
Classifier: Programming Language :: Python :: 3.11
Classifier: Programming Language :: Python :: 3.12
Classifier: Programming Language :: Python :: 3.13
Requires-Dist: altair (>=5.5.0,<6.0.0)
Requires-Dist: matplotlib (>=3.10.0,<4.0.0)
Requires-Dist: pandas (>=2.2.3,<3.0.0)
Requires-Dist: seaborn (>=0.13.2,<0.14.0)
